tinydb/__init__.py
tinydb/database.py
tinydb/middlewares.py
tinydb/mypy_plugin.py
tinydb/operations.py
tinydb/py.typed
tinydb/queries.py
tinydb/storages.py
tinydb/table.py
tinydb/utils.py
tinydb/version.py
fhtinydb-0.1.1.dist-info/METADATA
fhtinydb-0.1.1.dist-info/WHEEL
fhtinydb-0.1.1.dist-info/RECORD
